divdate
