Metadata-Version: 1.1
Name: divdate
Version: 0.2
Summary: Division based date/time building
Home-page: http://github.com/soxofaan/divdate
Author: Stefaan Lippens
Author-email: soxofaan@gmail.com
License: MIT
Keywords: date time datetime division operator
Platform: UNKNOWN
Classifier: License :: OSI Approved :: MIT License
